<!--Exported from Orchard-->
<Orchard>
    <Recipe>
        <Name>Basic Setup for Summit</Name>
        <Author>Carl Woodhouse</Author>
    </Recipe>
    <Data>
        <Layer Id="/Layer.LayerName=Default" Status="Published">
            <CommonPart Owner="/User.UserName=admin" CreatedUtc="2013-02-26T22:54:15Z" PublishedUtc="2013-02-26T22:54:15Z" ModifiedUtc="2013-02-26T22:54:15Z" />
            <LayerPart Name="Default" Description="The widgets in this layer are displayed on all pages" LayerRule="true" />
        </Layer>
        <Layer Id="/Layer.LayerName=TheHomepage" Status="Published">
            <CommonPart Owner="/User.UserName=admin" CreatedUtc="2013-02-24T22:18:33Z" PublishedUtc="2013-02-26T22:56:09Z" ModifiedUtc="2013-02-26T22:56:09Z" />
            <LayerPart Name="TheHomepage" Description="The widgets in this layer are displayed on the home page" LayerRule="url '~/'" />
        </Layer>
        <Query Id="/Identifier=86db832d76694d0d984d4380bc6f1b6f" Status="Published">
            <TitlePart Title="List of Active Concierges" />
            <IdentityPart Identifier="86db832d76694d0d984d4380bc6f1b6f" />
            <QueryPart>
                <FilterGroups>
                    <FilterGroup>
                        <Filter Category="ConciergePartContentFields" Description="" Position="0" State="&lt;Form&gt;&lt;Description&gt;&lt;/Description&gt;&lt;Value&gt;true&lt;/Value&gt;&lt;__RequestVerificationToken&gt;FyfoId5dssFre7z9rXry06le9o9dMJPcodEtI8w-pP64sSYswKBjmcfEfvF4QyulK8mm5zUzE68yePrnC61I1rFgXrH22TLczTEOj-YHlInAzbLNIYml_bMFAgSFVM_XPg2W4r-u53kABURyplD5ANFxUoJgrY8L706inzrz80Y1&lt;/__RequestVerificationToken&gt;&lt;/Form&gt;" Type="ConciergePart.Active." />
                    </FilterGroup>
                </FilterGroups>
                <SortCriteria />
                <Layouts />
            </QueryPart>
        </Query>
        <Query Id="/Identifier=edae15669ccd4f6e95501c1ea227386d" Status="Published">
            <TitlePart Title="Destinations" />
            <IdentityPart Identifier="edae15669ccd4f6e95501c1ea227386d" />
            <QueryPart>
                <FilterGroups>
                    <FilterGroup>
                        <Filter Category="Content" Description="" Position="0" State="&lt;Form&gt;&lt;Description&gt;&lt;/Description&gt;&lt;ContentTypes&gt;Destination&lt;/ContentTypes&gt;&lt;__RequestVerificationToken&gt;fjslBna4W6YTMy21RqrHXbnKPo95ySxdWVdlWtnfawy9fwL7NvlEbSRobYaxGoENAG2Zf5Mhlv30b3fgI7YdjZo_XAa0wavrfdAjYuRaU77WnnNTgbsXRtY7mGM2tnNl5aj9UmZJhuptnz1mXjAwirp-0GsTkUDG-mN8sVCIYbs1&lt;/__RequestVerificationToken&gt;&lt;/Form&gt;" Type="ContentTypes" />
                    </FilterGroup>
                </FilterGroups>
                <SortCriteria />
                <Layouts>
                    <Layout Category="Html" Description="Countries, Grouped By Region" State="&lt;Form&gt;&lt;QueryId&gt;17&lt;/QueryId&gt;&lt;Category&gt;Html&lt;/Category&gt;&lt;Type&gt;List&lt;/Type&gt;&lt;Description&gt;Countries, Grouped By Region&lt;/Description&gt;&lt;Display&gt;1&lt;/Display&gt;&lt;DisplayType&gt;Summary&lt;/DisplayType&gt;&lt;GroupPropertyId&gt;0&lt;/GroupPropertyId&gt;&lt;Order&gt;unordered&lt;/Order&gt;&lt;ListId&gt;&lt;/ListId&gt;&lt;ListClass&gt;&lt;/ListClass&gt;&lt;ItemClass&gt;&lt;/ItemClass&gt;&lt;__RequestVerificationToken&gt;8y0f0onQ2POeM_S-10nWcAZvQkSc9LYkICZrGCQ6Y8moEblz3JBh1O2cmIrRXQJmBvIuKtfgrXm4JqX0hTpNK4e66MAwFt9X_9PkQXR-6UV3kC__HhZYo5BWs-N_vrQmbTNcOPlZ1Ff9MqmaXB7gZGsst_DjJEXg6T2pZ-OwewE1&lt;/__RequestVerificationToken&gt;&lt;/Form&gt;" Display="1" DisplayType="Summary" Type="List">
                        <Properties>
                            <Property Category="DestinationPartContentFields" Description="" Position="0" State="&lt;Form&gt;&lt;Description&gt;&lt;/Description&gt;&lt;LinkToContent&gt;false&lt;/LinkToContent&gt;&lt;ExcludeFromDisplay&gt;true,false&lt;/ExcludeFromDisplay&gt;&lt;CreateLabel&gt;false&lt;/CreateLabel&gt;&lt;Label&gt;&lt;/Label&gt;&lt;CustomizePropertyHtml&gt;false&lt;/CustomizePropertyHtml&gt;&lt;CustomPropertyTag&gt;&lt;/CustomPropertyTag&gt;&lt;CustomPropertyCss&gt;&lt;/CustomPropertyCss&gt;&lt;CustomizeLabelHtml&gt;false&lt;/CustomizeLabelHtml&gt;&lt;CustomLabelTag&gt;&lt;/CustomLabelTag&gt;&lt;CustomLabelCss&gt;&lt;/CustomLabelCss&gt;&lt;CustomizeWrapperHtml&gt;false&lt;/CustomizeWrapperHtml&gt;&lt;CustomWrapperTag&gt;&lt;/CustomWrapperTag&gt;&lt;CustomWrapperCss&gt;&lt;/CustomWrapperCss&gt;&lt;NoResultText&gt;&lt;/NoResultText&gt;&lt;ZeroIsEmpty&gt;false&lt;/ZeroIsEmpty&gt;&lt;HideEmpty&gt;false&lt;/HideEmpty&gt;&lt;RewriteOutput&gt;false&lt;/RewriteOutput&gt;&lt;RewriteText&gt;&lt;/RewriteText&gt;&lt;TrimLength&gt;false&lt;/TrimLength&gt;&lt;MaxLength&gt;0&lt;/MaxLength&gt;&lt;TrimOnWordBoundary&gt;false&lt;/TrimOnWordBoundary&gt;&lt;AddEllipsis&gt;false&lt;/AddEllipsis&gt;&lt;StripHtmlTags&gt;false&lt;/StripHtmlTags&gt;&lt;TrimWhiteSpace&gt;false&lt;/TrimWhiteSpace&gt;&lt;PreserveLines&gt;false&lt;/PreserveLines&gt;&lt;__RequestVerificationToken&gt;LlHOnFw3Bk3ysr3oKxIfl9bWnjTyn52UhPeizd0jt2rWQrqpZR1Cwn-ua9rC1tqaL6yVvKVdlah1U7i7VlIb5E_KBD5Um9_-jjpqqsnTYVOPJfu-zjujhJdFkMjHAooJp6HXyNQYUklsA508zKF6LKypKJ22K1-tgqP_N5fRsfQ1&lt;/__RequestVerificationToken&gt;&lt;/Form&gt;" Type="DestinationPart.Region." AddEllipsis="false" CreateLabel="false" CustomLabelCss="" CustomLabelTag="" CustomPropertyCss="" CustomPropertyTag="" CustomWrapperCss="" CustomWrapperTag="" CustomizeLabelHtml="false" CustomizePropertyHtml="false" CustomizeWrapperHtml="false" ExcludeFromDisplay="true" HideEmpty="false" Label="" LinkToContent="false" MaxLength="0" NoResultText="" PreserveLines="false" RewriteOutput="false" RewriteText="" StripHtmlTags="false" TrimLength="false" TrimOnWordBoundary="false" TrimWhiteSpace="false" ZeroIsEmpty="false" />
                            <Property Category="DestinationPartContentFields" Description="" Position="1" State="&lt;Form&gt;&lt;Description&gt;&lt;/Description&gt;&lt;LinkToContent&gt;false&lt;/LinkToContent&gt;&lt;ExcludeFromDisplay&gt;false&lt;/ExcludeFromDisplay&gt;&lt;CreateLabel&gt;false&lt;/CreateLabel&gt;&lt;Label&gt;&lt;/Label&gt;&lt;CustomizePropertyHtml&gt;false&lt;/CustomizePropertyHtml&gt;&lt;CustomPropertyTag&gt;&lt;/CustomPropertyTag&gt;&lt;CustomPropertyCss&gt;&lt;/CustomPropertyCss&gt;&lt;CustomizeLabelHtml&gt;false&lt;/CustomizeLabelHtml&gt;&lt;CustomLabelTag&gt;&lt;/CustomLabelTag&gt;&lt;CustomLabelCss&gt;&lt;/CustomLabelCss&gt;&lt;CustomizeWrapperHtml&gt;false&lt;/CustomizeWrapperHtml&gt;&lt;CustomWrapperTag&gt;&lt;/CustomWrapperTag&gt;&lt;CustomWrapperCss&gt;&lt;/CustomWrapperCss&gt;&lt;NoResultText&gt;&lt;/NoResultText&gt;&lt;ZeroIsEmpty&gt;false&lt;/ZeroIsEmpty&gt;&lt;HideEmpty&gt;false&lt;/HideEmpty&gt;&lt;RewriteOutput&gt;true,false&lt;/RewriteOutput&gt;&lt;RewriteText&gt;&amp;lt;a href=&quot;/area?c={Text}&quot;&amp;gt;{Text}&amp;lt;/a&amp;gt;&lt;/RewriteText&gt;&lt;TrimLength&gt;false&lt;/TrimLength&gt;&lt;MaxLength&gt;0&lt;/MaxLength&gt;&lt;TrimOnWordBoundary&gt;false&lt;/TrimOnWordBoundary&gt;&lt;AddEllipsis&gt;false&lt;/AddEllipsis&gt;&lt;StripHtmlTags&gt;false&lt;/StripHtmlTags&gt;&lt;TrimWhiteSpace&gt;false&lt;/TrimWhiteSpace&gt;&lt;PreserveLines&gt;false&lt;/PreserveLines&gt;&lt;__RequestVerificationToken&gt;RQQfyo01LbjR0DlrXX9uyQh26dvLijqyWnxHLhhRNi7IK8dqDYoPCPnyCr72UlaJNAS_VNxmUUPBS3AHDMnjQ493OGkXnDVYK2dUmvSr4O91TMzIefgsSWnPfX_-0Wcmej_PWkStSE7m-p9uCTwOk7ufNxU63CzXN8PDFWLt9bQ1&lt;/__RequestVerificationToken&gt;&lt;/Form&gt;" Type="DestinationPart.Country." AddEllipsis="false" CreateLabel="false" CustomLabelCss="" CustomLabelTag="" CustomPropertyCss="" CustomPropertyTag="" CustomWrapperCss="" CustomWrapperTag="" CustomizeLabelHtml="false" CustomizePropertyHtml="false" CustomizeWrapperHtml="false" ExcludeFromDisplay="false" HideEmpty="false" Label="" LinkToContent="false" MaxLength="0" NoResultText="" PreserveLines="false" RewriteOutput="true" RewriteText="&lt;a href=&quot;/area?c={Text}&quot;&gt;{Text}&lt;/a&gt;" StripHtmlTags="false" TrimLength="false" TrimOnWordBoundary="false" TrimWhiteSpace="false" ZeroIsEmpty="false" />
                        </Properties>
                        <Group />
                    </Layout>
                </Layouts>
            </QueryPart>
        </Query>

        <ProjectionWidget Id="/Identifier=97d75435dc9c4dd79756e35afd325441" Status="Published">
            <CommonPart Owner="/User.UserName=admin" Container="/Layer.LayerName=TheHomepage" CreatedUtc="2013-02-26T19:26:44Z" PublishedUtc="2013-02-26T22:56:09Z" ModifiedUtc="2013-02-26T23:01:47Z" />
            <IdentityPart Identifier="97d75435dc9c4dd79756e35afd325441" />
            <WidgetPart Title="Destinations" Position="1" Zone="Content" RenderTitle="false" Name="homepage-destinations" />
            <ProjectionPart Items="16" ItemsPerPage="0" Offset="0" PagerSuffix="" MaxItems="0" DisplayPager="true" Query="/Identifier=edae15669ccd4f6e95501c1ea227386d" LayoutIndex="-1" />
        </ProjectionWidget>
        <TaxonomyMenu Id="" Status="Published">
            <TaxonomyMenuPart DisplayTopMenuItem="false" DisplayContentCount="false" LevelsToDisplay="0" HideEmptyTerms="true" TaxonomyPartRecordId="/alias=region" />
            <CommonPart Owner="/User.UserName=admin" Container="/Layer.LayerName=Default" CreatedUtc="2013-02-27T22:36:37Z" PublishedUtc="2013-02-27T22:36:37Z" ModifiedUtc="2013-02-27T22:36:37Z" />
            <WidgetPart Title="Region" Position="1" Zone="Content" RenderTitle="true" />
        </TaxonomyMenu>
        <SearchWidget Id="" Status="Published">
            <CommonPart Owner="/User.UserName=admin" Container="/Layer.LayerName=TheHomepage" CreatedUtc="2013-02-26T23:03:14Z" PublishedUtc="2013-02-26T23:03:14Z" ModifiedUtc="2013-02-26T23:03:14Z" />
            <WidgetPart Title="Search" Position="1" Zone="Featured" RenderTitle="false" />
        </SearchWidget>
    </Data>
</Orchard>